lolbin/__main__.py
lolbin/cli.py
lolbin-2.0.0.dist-info/METADATA
lolbin-2.0.0.dist-info/WHEEL
lolbin-2.0.0.dist-info/entry_points.txt
lolbin-2.0.0.dist-info/licenses/LICENSE
lolbin-2.0.0.dist-info/RECORD
