Metadata-Version: 2.4
Name: lolbin
Version: 2.0.0
Summary: A small python cli to manage paste.lol from cli
Project-URL: Homepage, https://git.ache.one/lolbin
Author-email: ache <ache@ache.one>
License-File: LICENSE
Classifier: License :: OSI Approved :: MIT License
Classifier: Operating System :: POSIX
Classifier: Programming Language :: Python :: 3
Requires-Python: >=3.10
Requires-Dist: humanize
Requires-Dist: requests
Requires-Dist: tomli
